Metadata-Version: 2.1
Name: kalculator
Version: 0.0.1
Summary: A very basic calculator
Home-page: https://github.com/KamilBatu
Author: kamil hasssen
Author-email: kh14053340@gmail.com
License: MIT
Keywords: calculator
Classifier: Development Status :: 5 - Production/Stable
Classifier: Intended Audience :: Education
Classifier: Operating System :: Microsoft :: Windows :: Windows 10
Classifier: License :: OSI Approved :: MIT License
Classifier: Programming Language :: Python :: 3
Requires-Python: >=3.6
License-File: LICENSE.txt
